knowledge_mcp/__init__.py
knowledge_mcp/cli.py
knowledge_mcp/config.py
knowledge_mcp/documents.py
knowledge_mcp/knowledgebases.py
knowledge_mcp/mcp_server.py
knowledge_mcp/openai_func.py
knowledge_mcp/rag.py
knowledge_mcp/shell.py
knowledge_mcp-0.4.1.dist-info/METADATA
knowledge_mcp-0.4.1.dist-info/WHEEL
knowledge_mcp-0.4.1.dist-info/entry_points.txt
knowledge_mcp-0.4.1.dist-info/licenses/LICENSE
knowledge_mcp-0.4.1.dist-info/RECORD
