Metadata-Version: 2.4
Name: knowledge-mcp
Version: 0.4.1
Summary: A MCP server designed to bridge the gap between specialized knowledge domains and AI assistants.
Project-URL: Homepage, https://github.com/olafgeibig/knowledge-mcp
Project-URL: Repository, https://github.com/olafgeibig/knowledge-mcp
Author-email: Olaf Geibig <olaf.geibig@gmail.com>
License: MIT
License-File: LICENSE
Keywords: cli,fastmcp,knowledge,lightrag,mcp,search
Classifier: Development Status :: 3 - Alpha
Classifier: Intended Audience :: Developers
Classifier: License :: OSI Approved :: MIT License
Classifier: Operating System :: OS Independent
Classifier: Programming Language :: Python :: 3
Classifier: Programming Language :: Python :: 3.12
Classifier: Topic :: Scientific/Engineering :: Artificial Intelligence
Classifier: Topic :: Software Development :: Libraries :: Python Modules
Classifier: Topic :: Text Processing :: Indexing
Requires-Python: <3.13,>=3.12
Requires-Dist: fastmcp>=2.2.1
Requires-Dist: graspologic>=3.4.1
Requires-Dist: lightrag-hku[api]>=1.4.0
Requires-Dist: markitdown[all,pdf]>=0.1.2
Requires-Dist: mineru>=2.0.6
Requires-Dist: nano-vectordb>=0.0.4.3
Requires-Dist: networkx>=3.4.2
Requires-Dist: openai>=1.75.0
Requires-Dist: pipmaster>=0.5.4
Requires-Dist: pydantic>=2.11.3
Requires-Dist: pyyaml>=6.0
Requires-Dist: raganything[all]>=1.0.4
Requires-Dist: six>=1.16.0
Requires-Dist: tenacity>=9.1.2
Requires-Dist: tiktoken>=0.9.0
Provides-Extra: dev
Requires-Dist: pip>=23.0.0; extra == 'dev'
Requires-Dist: pytest>=7.4.0; extra == 'dev'
